README
setup.py
brooklynmuseumapi/__init__.py
brooklynmuseumapi/request.py
brooklynmuseumapi.egg-info/PKG-INFO
brooklynmuseumapi.egg-info/SOURCES.txt
brooklynmuseumapi.egg-info/dependency_links.txt
brooklynmuseumapi.egg-info/top_level.txt