Metadata-Version: 1.0
Name: brooklynmuseumapi
Version: 0.1.0
Summary: Interact with the Brooklyn Museum Collection API
Home-page: http://bitbucket.org/anarchivist/brooklynmuseumapi
Author: Mark A. Matienzo
Author-email: mark@matienzo.org
License: GPL/BSD
Platform: UNKNOWN
Classifier: Intended Audience :: Education
Classifier: Intended Audience :: Developers
Classifier: Intended Audience :: Information Technology
Classifier: License :: OSI Approved :: GNU General Public License (GPL)
Classifier: Programming Language :: Python
Classifier: Development Status :: 3 - Alpha
